{"name": "ECEN 325 - Spring 22 - 201,507-512", "color": "rgb(162, 214, 161);", "assignments": [{"name": "Canvas Exam 1", "class": "ECEN 325 - Spring 22 - 201,507-512", "priority": 3, "dueDate": "2022-05-01T23:59", "startDate": "2022-05-01T23:59", "link": "https://canvas.tamu.edu/courses/134557/assignments/1201465", "relatedLinks": "", "googleLocation": "", "canvasLocation": "ECEN 325 - Spring 22 - 201,507-512", "complete": false, "notes": ""}, {"name": "Canvas Exam 2", "class": "ECEN 325 - Spring 22 - 201,507-512", "priority": 3, "dueDate": "2022-05-01T23:59", "startDate": "2022-05-01T23:59", "link": "https://canvas.tamu.edu/courses/134557/assignments/1225873", "relatedLinks": "", "googleLocation": "", "canvasLocation": "ECEN 325 - Spring 22 - 201,507-512", "complete": false, "notes": ""}, {"name": "Canvas In Class Question 4", "class": "ECEN 325 - Spring 22 - 201,507-512", "priority": 3, "dueDate": "2022-05-01T23:59", "startDate": "2022-04-08T11:30", "link": "https://canvas.tamu.edu/courses/134557/assignments/1219969", "relatedLinks": "", "googleLocation": "", "canvasLocation": "ECEN 325 - Spring 22 - 201,507-512", "complete": false, "notes": ""}], "order": 0}