[{"name": "CSCE315", "color": "rgb(162, 214, 161);", "assignments": [{"name": "Quiz1", "class": "CSCE315", "priority": 3, "dueDate": "2022-05-01T23:59", "startDate": "2022-04-15T01:49", "link": "https://classroom.google.com/c/NTAwMjk2MDEyNTU4/a/NTAwNzEyNjQ3NTQx/details", "relatedLinks": "", "notes": "Quiz1 dummy instructions", "googleLocation": "CSCE315", "canvasLocation": "", "complete": false}, {"name": "HW1", "class": "CSCE315", "priority": 3, "dueDate": "2022-05-13T23:59", "startDate": "2022-04-13T00:36", "link": "https://classroom.google.com/c/NTAwMjk2MDEyNTU4/a/NTAwMjk2MDEyNjI1/details", "relatedLinks": "", "notes": "This is a test HW assignment.\nThis would be the instructions of an assignment.", "googleLocation": "CSCE315", "canvasLocation": "", "complete": false}], "order": 0}, {"name": "Project 3 Demo Course", "color": "rgb(162, 214, 161);", "assignments": [{"name": "HW10", "class": "Project 3 Demo Course", "priority": 3, "dueDate": "2022-04-30T23:59", "startDate": "2022-04-13T16:59", "link": "https://classroom.google.com/c/MzU0NDUyMDYwODEy/a/NTAwNDQ5MTUzNDY4/details", "relatedLinks": "", "notes": "Upcoming HW instructions", "googleLocation": "Project 3 Demo Course", "canvasLocation": "", "complete": false}, {"name": "FINAL", "class": "Project 3 Demo Course", "priority": 3, "dueDate": "2022-05-19T23:59", "startDate": "2022-04-13T16:58", "link": "https://classroom.google.com/c/MzU0NDUyMDYwODEy/a/NTAwNDQ5MTUzMzQy/details", "relatedLinks": "", "notes": "Very difficult test, not fun.", "googleLocation": "Project 3 Demo Course", "canvasLocation": "", "complete": false}, {"name": "MIDTERM ", "class": "Project 3 Demo Course", "priority": 3, "dueDate": "2022-05-06T23:59", "startDate": "2022-04-13T16:57", "link": "https://classroom.google.com/c/MzU0NDUyMDYwODEy/a/NTAwNDQ5MTUzMTg5/details", "relatedLinks": "", "notes": "Whoa, its the instructions for my midterm!", "googleLocation": "Project 3 Demo Course", "canvasLocation": "", "complete": false}, {"name": "DEMO HW 1", "class": "Project 3 Demo Course", "priority": 3, "dueDate": "2022-05-01T23:59", "startDate": "2022-04-13T16:57", "link": "https://classroom.google.com/c/MzU0NDUyMDYwODEy/a/NTAwNDQ5MTUzMDY3/details", "relatedLinks": "", "notes": "Super cool instructions for my super cool demo assignment", "googleLocation": "Project 3 Demo Course", "canvasLocation": "", "complete": false}], "order": 1}]